{
    "101": {
        "2014-05-30": {
            "trades": [
                11213, 
                11218
            ]
        }, 
        "2014-06-05": {
            "trades": [
                16638
            ]
        }, 
        "2014-06-10": {
            "trades": [
                19360
            ]
        }
    }, 
    "1146": {
        "2014-06-05": {
            "comments": [
                1310
            ]
        }, 
        "2014-06-13": {
            "trades": [
                23146, 
                23145
            ]
        }
    }, 
    "122": {
        "2014-05-29": {
            "trades": [
                10745, 
                11059
            ]
        }
    }, 
    "1259": {
        "2014-05-27": {
            "trades": [
                9834, 
                9831, 
                9833, 
                9832
            ]
        }
    }, 
    "1285": {
        "2014-06-12": {
            "comments": [
                1683
            ], 
            "trades": [
                22757
            ]
        }
    }, 
    "1292": {
        "2014-06-13": {
            "trades": [
                23171
            ]
        }
    }, 
    "1319": {
        "2014-05-27": {
            "trades": [
                9848, 
                9847
            ]
        }
    }, 
    "1354": {
        "2014-06-03": {
            "trades": [
                14421
            ]
        }, 
        "2014-06-05": {
            "trades": [
                16494
            ]
        }
    }, 
    "1397": {
        "2014-06-06": {
            "trades": [
                16708
            ]
        }
    }, 
    "14": {
        "2014-06-21": {
            "trades": [
                33368, 
                33408
            ]
        }
    }, 
    "1568": {
        "2014-05-27": {
            "comments": [
                1045
            ]
        }
    }, 
    "1573": {
        "2014-06-19": {
            "trades": [
                31259, 
                31260
            ]
        }
    }, 
    "1607": {
        "2014-05-29": {
            "trades": [
                11048, 
                10735
            ]
        }, 
        "2014-06-06": {
            "trades": [
                16679
            ]
        }, 
        "2014-06-07": {
            "trades": [
                17642
            ]
        }
    }, 
    "171": {
        "2014-05-29": {
            "trades": [
                10801
            ]
        }
    }, 
    "1740": {
        "2014-06-07": {
            "trades": [
                18124
            ]
        }
    }, 
    "176": {
        "2014-05-29": {
            "trades": [
                11057, 
                10821, 
                10932, 
                11045
            ]
        }, 
        "2014-05-30": {
            "trades": [
                11164, 
                11184, 
                11070, 
                11166, 
                11174
            ]
        }, 
        "2014-05-31": {
            "trades": [
                12473, 
                12481
            ]
        }, 
        "2014-06-07": {
            "trades": [
                17708
            ]
        }, 
        "2014-06-10": {
            "trades": [
                19389
            ]
        }, 
        "2014-06-12": {
            "comments": [
                1665
            ]
        }, 
        "2014-06-13": {
            "trades": [
                23185, 
                23220
            ]
        }, 
        "2014-06-14": {
            "comments": [
                1750, 
                1774
            ], 
            "trades": [
                23965
            ]
        }, 
        "2014-06-17": {
            "comments": [
                1903, 
                1913, 
                1907
            ]
        }
    }, 
    "1879": {
        "2014-06-12": {
            "trades": [
                22895
            ]
        }
    }, 
    "1880": {
        "2014-05-30": {
            "trades": [
                11253
            ]
        }, 
        "2014-06-10": {
            "trades": [
                19208
            ]
        }
    }, 
    "1881": {
        "2014-05-31": {
            "trades": [
                12368
            ]
        }
    }, 
    "1901": {
        "2014-06-10": {
            "trades": [
                19306
            ]
        }
    }, 
    "1932": {
        "2014-06-06": {
            "trades": [
                16767, 
                16769
            ]
        }
    }, 
    "1939": {
        "2014-05-28": {
            "trades": [
                10448
            ]
        }, 
        "2014-06-12": {
            "trades": [
                22733
            ]
        }
    }, 
    "1947": {
        "2014-05-31": {
            "trades": [
                11971
            ]
        }, 
        "2014-06-04": {
            "trades": [
                14828, 
                14807
            ]
        }, 
        "2014-06-11": {
            "trades": [
                20404, 
                20347
            ]
        }, 
        "2014-06-14": {
            "trades": [
                24627
            ]
        }
    }, 
    "1960": {
        "2014-05-27": {
            "trades": [
                9835
            ]
        }
    }, 
    "1964": {
        "2014-05-27": {
            "trades": [
                9852, 
                9853
            ]
        }
    }, 
    "1968": {
        "2014-05-28": {
            "trades": [
                10100, 
                10105, 
                10123
            ]
        }, 
        "2014-06-04": {
            "trades": [
                15186, 
                15200, 
                15194
            ]
        }, 
        "2014-06-06": {
            "trades": [
                16774, 
                16772, 
                16773
            ]
        }, 
        "2014-06-07": {
            "comments": [
                1439
            ], 
            "trades": [
                18363
            ]
        }, 
        "2014-06-11": {
            "trades": [
                22036, 
                22042
            ]
        }
    }, 
    "1971": {
        "2014-05-31": {
            "trades": [
                13118
            ]
        }
    }, 
    "1979": {
        "2014-06-05": {
            "trades": [
                16491
            ]
        }
    }, 
    "1981": {
        "2014-05-28": {
            "trades": [
                10409, 
                10410, 
                10426
            ]
        }, 
        "2014-05-31": {
            "trades": [
                11756, 
                11782, 
                12130, 
                11835, 
                12118, 
                12316, 
                11742, 
                11740, 
                11856
            ]
        }, 
        "2014-06-04": {
            "trades": [
                15170, 
                16124, 
                15860, 
                16125, 
                15909, 
                14624, 
                16123, 
                15139, 
                14516
            ]
        }, 
        "2014-06-07": {
            "trades": [
                17123
            ]
        }, 
        "2014-06-11": {
            "trades": [
                21033, 
                21823, 
                20994, 
                20405, 
                21855
            ]
        }, 
        "2014-06-14": {
            "trades": [
                24181, 
                24229, 
                25375
            ]
        }, 
        "2014-06-18": {
            "trades": [
                27981, 
                27930, 
                30172, 
                30192, 
                28336
            ]
        }
    }, 
    "1993": {
        "2014-06-11": {
            "trades": [
                19940
            ]
        }
    }, 
    "20": {
        "2014-05-30": {
            "trades": [
                11300
            ]
        }
    }, 
    "2003": {
        "2014-05-27": {
            "trades": [
                9851
            ]
        }, 
        "2014-05-31": {
            "trades": [
                13359
            ]
        }
    }, 
    "2011": {
        "2014-05-29": {
            "trades": [
                10774
            ]
        }, 
        "2014-06-20": {
            "trades": [
                31657
            ]
        }
    }, 
    "2015": {
        "2014-05-28": {
            "trades": [
                10666
            ]
        }, 
        "2014-05-29": {
            "trades": [
                11063
            ]
        }, 
        "2014-05-30": {
            "trades": [
                11330, 
                11331
            ]
        }
    }, 
    "2026": {
        "2014-05-29": {
            "trades": [
                10788, 
                10789
            ]
        }, 
        "2014-05-31": {
            "trades": [
                12878, 
                12860, 
                12888
            ]
        }, 
        "2014-06-07": {
            "trades": [
                17080, 
                17066
            ]
        }, 
        "2014-06-11": {
            "trades": [
                19949, 
                20370, 
                20129
            ]
        }, 
        "2014-06-14": {
            "trades": [
                24044, 
                23903, 
                23939
            ]
        }, 
        "2014-06-21": {
            "trades": [
                33042, 
                36490, 
                33016, 
                33029
            ]
        }
    }, 
    "2033": {
        "2014-05-27": {
            "trades": [
                9860, 
                9863, 
                9862
            ]
        }, 
        "2014-05-28": {
            "trades": [
                9871, 
                9893, 
                10536, 
                10345, 
                9897, 
                10322, 
                10300, 
                9890
            ]
        }, 
        "2014-05-30": {
            "trades": [
                11343, 
                11342
            ]
        }, 
        "2014-05-31": {
            "trades": [
                12611
            ]
        }, 
        "2014-06-04": {
            "trades": [
                15325
            ]
        }
    }, 
    "2044": {
        "2014-05-27": {
            "trades": [
                9836
            ]
        }
    }, 
    "2055": {
        "2014-05-27": {
            "trades": [
                9864, 
                9858, 
                9857, 
                9861, 
                9856, 
                9859
            ]
        }, 
        "2014-05-28": {
            "trades": [
                10397, 
                9891
            ]
        }
    }, 
    "2056": {
        "2014-05-30": {
            "trades": [
                11093, 
                11094
            ]
        }
    }, 
    "2058": {
        "2014-05-28": {
            "trades": [
                9952, 
                9935, 
                9965, 
                9961, 
                9959, 
                10140
            ]
        }, 
        "2014-05-30": {
            "trades": [
                11143, 
                11137
            ]
        }, 
        "2014-05-31": {
            "trades": [
                12565, 
                12298, 
                12852, 
                12767, 
                12308
            ]
        }, 
        "2014-06-03": {
            "trades": [
                14416
            ]
        }, 
        "2014-06-04": {
            "trades": [
                14680
            ]
        }, 
        "2014-06-05": {
            "trades": [
                16488, 
                16328, 
                16547
            ]
        }, 
        "2014-06-07": {
            "comments": [
                1441
            ], 
            "trades": [
                17756, 
                17454, 
                17458, 
                17777, 
                17727
            ]
        }
    }, 
    "2061": {
        "2014-05-28": {
            "trades": [
                10413, 
                9980, 
                9988, 
                9979
            ]
        }
    }, 
    "2062": {
        "2014-05-28": {
            "trades": [
                10144, 
                10165, 
                10147, 
                10066, 
                10103, 
                10478, 
                10219, 
                10453, 
                10208, 
                10210, 
                10230, 
                10153, 
                10695, 
                10139, 
                10689, 
                10232, 
                10226, 
                10280
            ]
        }, 
        "2014-05-29": {
            "trades": [
                11007, 
                10952, 
                11008, 
                10835
            ]
        }, 
        "2014-05-30": {
            "trades": [
                11261, 
                11244, 
                11090, 
                11338, 
                11295, 
                11073, 
                11080, 
                11298, 
                11311, 
                11076, 
                11287, 
                11237, 
                11301, 
                11245, 
                11294, 
                11189
            ]
        }, 
        "2014-05-31": {
            "trades": [
                12423, 
                13183, 
                12499, 
                11765, 
                12845, 
                13280, 
                13549, 
                12982, 
                11807, 
                13308, 
                13773, 
                11767, 
                13184, 
                13951, 
                13872
            ]
        }, 
        "2014-06-03": {
            "comments": [
                1211
            ], 
            "trades": [
                14315, 
                14389, 
                14375, 
                14316, 
                14403
            ]
        }, 
        "2014-06-04": {
            "trades": [
                15805, 
                15722, 
                15536, 
                15936, 
                15765, 
                15824, 
                14904, 
                14959, 
                14895, 
                15773, 
                15334
            ]
        }, 
        "2014-06-05": {
            "comments": [
                1289, 
                1308
            ], 
            "trades": [
                16626, 
                16464, 
                16479, 
                16469, 
                16260, 
                16446, 
                16288, 
                16624, 
                16253, 
                16470, 
                16659, 
                16468, 
                16368, 
                16620, 
                16492, 
                16578, 
                16447, 
                16507, 
                16486
            ]
        }, 
        "2014-06-06": {
            "trades": [
                16719, 
                16717, 
                16703, 
                16718
            ]
        }, 
        "2014-06-07": {
            "trades": [
                17567, 
                17503, 
                17546, 
                18212, 
                17604, 
                17596, 
                17500, 
                17563, 
                17554, 
                17196, 
                17570, 
                17259
            ]
        }, 
        "2014-06-10": {
            "trades": [
                19169, 
                19352, 
                19350, 
                19172
            ]
        }, 
        "2014-06-11": {
            "trades": [
                20580, 
                20940, 
                20700, 
                20482, 
                19603, 
                20585, 
                20492
            ]
        }, 
        "2014-06-12": {
            "comments": [
                1708
            ], 
            "trades": [
                22796, 
                22787, 
                22753, 
                22891, 
                22684
            ]
        }, 
        "2014-06-13": {
            "comments": [
                1728
            ], 
            "trades": [
                23015, 
                23007, 
                23045
            ]
        }, 
        "2014-06-14": {
            "trades": [
                24025, 
                24174, 
                23958, 
                24090, 
                23911
            ]
        }
    }, 
    "2063": {
        "2014-05-28": {
            "trades": [
                10051
            ]
        }
    }, 
    "2070": {
        "2014-05-29": {
            "trades": [
                10769
            ]
        }
    }, 
    "2074": {
        "2014-06-11": {
            "trades": [
                20140, 
                20086, 
                20162
            ]
        }, 
        "2014-06-14": {
            "trades": [
                24453, 
                24335, 
                24241
            ]
        }, 
        "2014-06-18": {
            "trades": [
                28142
            ]
        }
    }, 
    "2075": {
        "2014-05-29": {
            "trades": [
                10827
            ]
        }, 
        "2014-05-31": {
            "trades": [
                13174, 
                13160
            ]
        }, 
        "2014-06-04": {
            "trades": [
                15253, 
                15647, 
                15254, 
                15737, 
                15708
            ]
        }, 
        "2014-06-07": {
            "trades": [
                18659, 
                17673, 
                17699, 
                18710, 
                18727, 
                18787
            ]
        }, 
        "2014-06-11": {
            "trades": [
                22412
            ]
        }, 
        "2014-06-13": {
            "comments": [
                1719
            ]
        }, 
        "2014-06-14": {
            "comments": [
                1840
            ], 
            "trades": [
                23432, 
                26080, 
                26312, 
                24677, 
                25289, 
                23266
            ]
        }, 
        "2014-06-18": {
            "trades": [
                28914, 
                28820
            ]
        }, 
        "2014-06-19": {
            "trades": [
                31414
            ]
        }, 
        "2014-06-20": {
            "trades": [
                31914
            ]
        }, 
        "2014-06-21": {
            "trades": [
                34885, 
                35492
            ]
        }
    }, 
    "2076": {
        "2014-05-29": {
            "trades": [
                10830
            ]
        }, 
        "2014-05-30": {
            "trades": [
                11267
            ]
        }
    }, 
    "2080": {
        "2014-05-29": {
            "trades": [
                10848, 
                10922, 
                10854, 
                10918
            ]
        }, 
        "2014-06-07": {
            "trades": [
                17581
            ]
        }, 
        "2014-06-11": {
            "trades": [
                21340
            ]
        }, 
        "2014-06-12": {
            "trades": [
                22801
            ]
        }, 
        "2014-06-19": {
            "trades": [
                31476, 
                31469
            ]
        }
    }, 
    "2081": {
        "2014-05-29": {
            "trades": [
                10845
            ]
        }
    }, 
    "2083": {
        "2014-05-29": {
            "trades": [
                10850
            ]
        }
    }, 
    "2084": {
        "2014-05-29": {
            "trades": [
                10868, 
                10853
            ]
        }, 
        "2014-05-31": {
            "trades": [
                13852, 
                12797
            ]
        }, 
        "2014-06-03": {
            "trades": [
                14354, 
                14342, 
                14348, 
                14359, 
                14371, 
                14327, 
                14319, 
                14322, 
                14336
            ]
        }, 
        "2014-06-04": {
            "trades": [
                15970, 
                15612, 
                15978
            ]
        }, 
        "2014-06-07": {
            "trades": [
                18815
            ]
        }, 
        "2014-06-11": {
            "trades": [
                20526, 
                20170, 
                20588
            ]
        }, 
        "2014-06-14": {
            "trades": [
                25126, 
                25193
            ]
        }, 
        "2014-06-18": {
            "trades": [
                31131, 
                30126, 
                31067
            ]
        }
    }, 
    "2085": {
        "2014-05-29": {
            "comments": [
                1082
            ], 
            "trades": [
                10852, 
                10867, 
                10872, 
                10897
            ]
        }, 
        "2014-05-31": {
            "trades": [
                12633, 
                12746
            ]
        }, 
        "2014-06-04": {
            "comments": [
                1276
            ], 
            "trades": [
                16064, 
                15872, 
                16047
            ]
        }, 
        "2014-06-07": {
            "trades": [
                18060
            ]
        }, 
        "2014-06-11": {
            "comments": [
                1630
            ], 
            "trades": [
                22248, 
                22308, 
                22281, 
                22341, 
                22199
            ]
        }, 
        "2014-06-18": {
            "trades": [
                28490, 
                28389
            ]
        }
    }, 
    "2086": {
        "2014-05-29": {
            "trades": [
                10873
            ]
        }
    }, 
    "2089": {
        "2014-05-29": {
            "trades": [
                10883
            ]
        }
    }, 
    "2090": {
        "2014-05-29": {
            "trades": [
                10895, 
                10886, 
                10894, 
                10882
            ]
        }
    }, 
    "2092": {
        "2014-05-29": {
            "trades": [
                10912, 
                10916
            ]
        }
    }, 
    "2095": {
        "2014-05-29": {
            "trades": [
                10928
            ]
        }
    }, 
    "2098": {
        "2014-06-12": {
            "trades": [
                22913
            ]
        }
    }, 
    "2100": {
        "2014-05-29": {
            "trades": [
                10944
            ]
        }, 
        "2014-05-30": {
            "trades": [
                11260, 
                11255
            ]
        }, 
        "2014-06-03": {
            "trades": [
                14404, 
                14405
            ]
        }
    }, 
    "2104": {
        "2014-05-29": {
            "trades": [
                10965
            ]
        }
    }, 
    "2108": {
        "2014-05-30": {
            "trades": [
                11158, 
                11157
            ]
        }
    }, 
    "2111": {
        "2014-05-31": {
            "trades": [
                12641, 
                12608
            ]
        }, 
        "2014-06-07": {
            "trades": [
                18510, 
                18516, 
                18219, 
                18290
            ]
        }, 
        "2014-06-11": {
            "trades": [
                21443, 
                21320
            ]
        }
    }, 
    "2113": {
        "2014-06-04": {
            "trades": [
                15328, 
                16189, 
                15208, 
                15251, 
                15220, 
                15259
            ]
        }, 
        "2014-06-07": {
            "trades": [
                17423, 
                17984, 
                17767, 
                17897, 
                17490, 
                18026
            ]
        }, 
        "2014-06-11": {
            "trades": [
                19590, 
                22155
            ]
        }, 
        "2014-06-14": {
            "trades": [
                23492, 
                23474, 
                25435, 
                25585, 
                25463
            ]
        }, 
        "2014-06-18": {
            "trades": [
                29516, 
                30291, 
                28320, 
                29956, 
                27677, 
                28816, 
                27644, 
                27611
            ]
        }, 
        "2014-06-21": {
            "trades": [
                32372, 
                32356, 
                32559, 
                32593, 
                33225
            ]
        }
    }, 
    "2124": {
        "2014-06-03": {
            "trades": [
                14338, 
                14325
            ]
        }, 
        "2014-06-05": {
            "trades": [
                16358
            ]
        }
    }, 
    "2125": {
        "2014-06-03": {
            "comments": [
                1205, 
                1204
            ], 
            "trades": [
                14373, 
                14372
            ]
        }
    }, 
    "2129": {
        "2014-06-04": {
            "trades": [
                14454
            ]
        }
    }, 
    "2132": {
        "2014-06-04": {
            "trades": [
                15440
            ]
        }
    }, 
    "2134": {
        "2014-06-04": {
            "trades": [
                15677
            ]
        }, 
        "2014-06-07": {
            "trades": [
                17404, 
                17384
            ]
        }, 
        "2014-06-11": {
            "trades": [
                20669
            ]
        }, 
        "2014-06-14": {
            "trades": [
                24916
            ]
        }, 
        "2014-06-21": {
            "trades": [
                35192
            ]
        }
    }, 
    "2143": {
        "2014-06-05": {
            "trades": [
                16354
            ]
        }
    }, 
    "2147": {
        "2014-06-05": {
            "trades": [
                16457
            ]
        }
    }, 
    "2148": {
        "2014-06-05": {
            "trades": [
                16481
            ]
        }
    }, 
    "2150": {
        "2014-06-07": {
            "trades": [
                17506, 
                17504, 
                17521
            ]
        }, 
        "2014-06-11": {
            "comments": [
                1589
            ], 
            "trades": [
                22316, 
                21981
            ]
        }, 
        "2014-06-12": {
            "comments": [
                1658, 
                1661
            ], 
            "trades": [
                22586, 
                22659, 
                22623, 
                22626, 
                22605
            ]
        }, 
        "2014-06-14": {
            "trades": [
                26017, 
                25959, 
                26099, 
                25948
            ]
        }, 
        "2014-06-18": {
            "trades": [
                30440, 
                30971, 
                30820, 
                30446
            ]
        }, 
        "2014-06-21": {
            "trades": [
                35817, 
                35805, 
                35774
            ]
        }
    }, 
    "2153": {
        "2014-06-05": {
            "trades": [
                16647
            ]
        }
    }, 
    "2158": {
        "2014-06-06": {
            "trades": [
                16684
            ]
        }
    }, 
    "2174": {
        "2014-06-06": {
            "trades": [
                16746
            ]
        }
    }, 
    "2176": {
        "2014-06-06": {
            "trades": [
                16749
            ]
        }
    }, 
    "2179": {
        "2014-06-18": {
            "trades": [
                29661, 
                29614, 
                30118, 
                29604
            ]
        }, 
        "2014-06-21": {
            "trades": [
                32307, 
                32603
            ]
        }
    }, 
    "218": {
        "2014-05-31": {
            "trades": [
                12895
            ]
        }, 
        "2014-06-06": {
            "trades": [
                16754, 
                16697, 
                16753
            ]
        }
    }, 
    "2182": {
        "2014-06-07": {
            "trades": [
                17575, 
                17607
            ]
        }, 
        "2014-06-11": {
            "trades": [
                20737
            ]
        }
    }, 
    "2185": {
        "2014-06-07": {
            "trades": [
                18765, 
                18698, 
                18685
            ]
        }, 
        "2014-06-11": {
            "trades": [
                22314, 
                22327, 
                22556
            ]
        }, 
        "2014-06-14": {
            "trades": [
                25848
            ]
        }, 
        "2014-06-18": {
            "trades": [
                31201, 
                31100, 
                31063, 
                31183, 
                31090, 
                31029
            ]
        }, 
        "2014-06-21": {
            "trades": [
                34526, 
                35077, 
                34908, 
                34972
            ]
        }
    }, 
    "2190": {
        "2014-06-10": {
            "trades": [
                19278, 
                19234, 
                19147, 
                19395, 
                19148, 
                19192, 
                19237, 
                19376, 
                19194, 
                19280, 
                19168
            ]
        }, 
        "2014-06-11": {
            "trades": [
                21386, 
                19932, 
                22094, 
                19609, 
                20620
            ]
        }, 
        "2014-06-12": {
            "trades": [
                22943, 
                22880, 
                22723
            ]
        }, 
        "2014-06-13": {
            "trades": [
                22981
            ]
        }, 
        "2014-06-14": {
            "trades": [
                23315, 
                23527, 
                23363, 
                23291, 
                25277
            ]
        }, 
        "2014-06-18": {
            "trades": [
                27248, 
                27403
            ]
        }, 
        "2014-06-19": {
            "trades": [
                31511
            ]
        }, 
        "2014-06-20": {
            "trades": [
                31951
            ]
        }, 
        "2014-06-21": {
            "trades": [
                32928, 
                32705, 
                32903
            ]
        }
    }, 
    "2193": {
        "2014-06-10": {
            "trades": [
                19221, 
                19267, 
                19245, 
                19209, 
                19254, 
                19269, 
                19228, 
                19271, 
                19252
            ]
        }
    }, 
    "2197": {
        "2014-06-10": {
            "trades": [
                19401
            ]
        }
    }, 
    "2199": {
        "2014-06-17": {
            "trades": [
                26964
            ]
        }
    }, 
    "2209": {
        "2014-06-11": {
            "trades": [
                22208
            ]
        }
    }, 
    "2214": {
        "2014-06-12": {
            "trades": [
                22719
            ]
        }
    }, 
    "2221": {
        "2014-06-12": {
            "trades": [
                22728
            ]
        }
    }, 
    "2225": {
        "2014-06-12": {
            "trades": [
                22737, 
                22736
            ]
        }
    }, 
    "2229": {
        "2014-06-12": {
            "trades": [
                22739
            ]
        }
    }, 
    "2244": {
        "2014-06-12": {
            "trades": [
                22834
            ]
        }
    }, 
    "2250": {
        "2014-06-12": {
            "trades": [
                22842
            ]
        }
    }, 
    "2252": {
        "2014-06-12": {
            "trades": [
                22848
            ]
        }
    }, 
    "2268": {
        "2014-06-13": {
            "trades": [
                22979
            ]
        }
    }, 
    "2270": {
        "2014-06-13": {
            "trades": [
                22986
            ]
        }
    }, 
    "2275": {
        "2014-06-13": {
            "trades": [
                23060, 
                23055, 
                23056, 
                23057
            ]
        }
    }, 
    "2276": {
        "2014-06-13": {
            "comments": [
                1724
            ], 
            "trades": [
                23176, 
                23075, 
                23101, 
                23211, 
                23137, 
                23175, 
                23149, 
                23109
            ]
        }, 
        "2014-06-14": {
            "trades": [
                25294, 
                25988, 
                25197, 
                25205, 
                25150
            ]
        }, 
        "2014-06-17": {
            "trades": [
                27059, 
                27054, 
                27063, 
                27037, 
                27040, 
                27071, 
                27036, 
                27052, 
                27050, 
                27047, 
                27056
            ]
        }, 
        "2014-06-18": {
            "trades": [
                27745, 
                27864, 
                27823, 
                29944
            ]
        }
    }, 
    "2283": {
        "2014-06-13": {
            "trades": [
                23234
            ]
        }, 
        "2014-06-14": {
            "trades": [
                25833, 
                23749, 
                25411, 
                24445, 
                24460
            ]
        }, 
        "2014-06-19": {
            "trades": [
                31594, 
                31588, 
                31530, 
                31536, 
                31529, 
                31515, 
                31514, 
                31540, 
                31543, 
                31521
            ]
        }, 
        "2014-06-20": {
            "trades": [
                31862
            ]
        }, 
        "2014-06-21": {
            "trades": [
                33047, 
                33300, 
                33716
            ]
        }
    }, 
    "2284": {
        "2014-06-13": {
            "trades": [
                23231
            ]
        }
    }, 
    "2285": {
        "2014-06-18": {
            "trades": [
                29256, 
                29196, 
                29186, 
                29421, 
                29274, 
                29411
            ]
        }, 
        "2014-06-21": {
            "trades": [
                36734, 
                36389, 
                36755, 
                36609
            ]
        }
    }, 
    "2289": {
        "2014-06-14": {
            "trades": [
                24966
            ]
        }, 
        "2014-06-20": {
            "comments": [
                2085
            ]
        }
    }, 
    "2299": {
        "2014-06-18": {
            "trades": [
                27513, 
                29476, 
                27505
            ]
        }, 
        "2014-06-19": {
            "trades": [
                31347, 
                31567, 
                31423, 
                31337, 
                31336, 
                31573, 
                31438, 
                31571, 
                31351, 
                31317, 
                31339, 
                31321
            ]
        }, 
        "2014-06-20": {
            "trades": [
                31947, 
                31867
            ]
        }, 
        "2014-06-21": {
            "trades": [
                36697, 
                37103, 
                32042, 
                32146, 
                31996, 
                36404, 
                36690, 
                32073, 
                32121, 
                36812
            ]
        }
    }, 
    "230": {
        "2014-05-28": {
            "trades": [
                10186
            ]
        }
    }, 
    "2315": {
        "2014-06-17": {
            "trades": [
                27110, 
                27126, 
                27130, 
                27115, 
                27114, 
                27099, 
                27123, 
                26968, 
                27109, 
                26965
            ]
        }, 
        "2014-06-18": {
            "trades": [
                28572
            ]
        }, 
        "2014-06-19": {
            "comments": [
                2050
            ], 
            "trades": [
                31360, 
                31419
            ]
        }, 
        "2014-06-20": {
            "trades": [
                31911
            ]
        }, 
        "2014-06-21": {
            "trades": [
                34876
            ]
        }
    }, 
    "2316": {
        "2014-06-17": {
            "trades": [
                26983
            ]
        }
    }, 
    "2352": {
        "2014-06-18": {
            "trades": [
                29488, 
                29455
            ]
        }
    }, 
    "2359": {
        "2014-06-18": {
            "comments": [
                1993
            ], 
            "trades": [
                29518
            ]
        }, 
        "2014-06-21": {
            "trades": [
                37041, 
                37186
            ]
        }
    }, 
    "2398": {
        "2014-06-19": {
            "trades": [
                31355, 
                31358
            ]
        }
    }, 
    "2400": {
        "2014-06-19": {
            "trades": [
                31361
            ]
        }
    }, 
    "2401": {
        "2014-06-19": {
            "trades": [
                31418, 
                31410, 
                31420, 
                31417
            ]
        }
    }, 
    "2415": {
        "2014-06-19": {
            "trades": [
                31483
            ]
        }
    }, 
    "2417": {
        "2014-06-19": {
            "trades": [
                31550
            ]
        }
    }, 
    "2418": {
        "2014-06-19": {
            "trades": [
                31557, 
                31558
            ]
        }
    }, 
    "2419": {
        "2014-06-19": {
            "trades": [
                31563
            ]
        }
    }, 
    "2430": {
        "2014-06-19": {
            "trades": [
                31585
            ]
        }
    }, 
    "2435": {
        "2014-06-20": {
            "trades": [
                31624
            ]
        }
    }, 
    "2437": {
        "2014-06-20": {
            "trades": [
                31635
            ]
        }
    }, 
    "2441": {
        "2014-06-20": {
            "trades": [
                31638
            ]
        }
    }, 
    "2442": {
        "2014-06-20": {
            "trades": [
                31642
            ]
        }
    }, 
    "2449": {
        "2014-06-20": {
            "trades": [
                31748, 
                31745
            ]
        }
    }, 
    "2458": {
        "2014-06-20": {
            "trades": [
                31764
            ]
        }
    }, 
    "2471": {
        "2014-06-20": {
            "trades": [
                31771
            ]
        }
    }, 
    "2499": {
        "2014-06-20": {
            "trades": [
                31782
            ]
        }
    }, 
    "2527": {
        "2014-06-20": {
            "trades": [
                31830
            ]
        }
    }, 
    "2532": {
        "2014-06-20": {
            "trades": [
                31832
            ]
        }
    }, 
    "2541": {
        "2014-06-20": {
            "trades": [
                31843
            ]
        }
    }, 
    "2545": {
        "2014-06-20": {
            "trades": [
                31849
            ]
        }
    }, 
    "2546": {
        "2014-06-20": {
            "trades": [
                31846
            ]
        }
    }, 
    "2563": {
        "2014-06-20": {
            "trades": [
                31860
            ]
        }
    }, 
    "2566": {
        "2014-06-20": {
            "trades": [
                31869
            ]
        }
    }, 
    "2567": {
        "2014-06-20": {
            "trades": [
                31880, 
                31875, 
                31877
            ]
        }
    }, 
    "2569": {
        "2014-06-20": {
            "trades": [
                31878
            ]
        }
    }, 
    "2578": {
        "2014-06-20": {
            "trades": [
                31893
            ]
        }
    }, 
    "2579": {
        "2014-06-20": {
            "trades": [
                31894
            ]
        }
    }, 
    "2581": {
        "2014-06-20": {
            "trades": [
                31897
            ]
        }
    }, 
    "2585": {
        "2014-06-20": {
            "trades": [
                31898
            ]
        }
    }, 
    "2589": {
        "2014-06-20": {
            "trades": [
                31900
            ]
        }
    }, 
    "2608": {
        "2014-06-20": {
            "trades": [
                31953
            ]
        }
    }, 
    "2609": {
        "2014-06-20": {
            "trades": [
                31954
            ]
        }
    }, 
    "2611": {
        "2014-06-20": {
            "trades": [
                31956
            ]
        }
    }, 
    "2673": {
        "2014-06-21": {
            "trades": [
                32188
            ]
        }
    }, 
    "2695": {
        "2014-06-21": {
            "trades": [
                32263
            ]
        }
    }, 
    "276": {
        "2014-05-28": {
            "trades": [
                10559, 
                10567
            ]
        }, 
        "2014-06-06": {
            "trades": [
                16682, 
                16681
            ]
        }, 
        "2014-06-11": {
            "comments": [
                1592
            ], 
            "trades": [
                21695, 
                21708
            ]
        }, 
        "2014-06-13": {
            "trades": [
                23168
            ]
        }, 
        "2014-06-14": {
            "comments": [
                1839
            ]
        }
    }, 
    "2796": {
        "2014-06-21": {
            "trades": [
                33488
            ]
        }
    }, 
    "2804": {
        "2014-06-21": {
            "trades": [
                33508
            ]
        }
    }, 
    "288": {
        "2014-06-13": {
            "trades": [
                22994
            ]
        }
    }, 
    "296": {
        "2014-05-27": {
            "trades": [
                9846
            ]
        }, 
        "2014-05-28": {
            "trades": [
                9938
            ]
        }, 
        "2014-05-30": {
            "trades": [
                11291
            ]
        }, 
        "2014-06-03": {
            "trades": [
                14415
            ]
        }, 
        "2014-06-04": {
            "trades": [
                15990, 
                15155
            ]
        }, 
        "2014-06-05": {
            "trades": [
                16611, 
                16615, 
                16583
            ]
        }, 
        "2014-06-06": {
            "comments": [
                1332
            ], 
            "trades": [
                16755, 
                16696, 
                16731, 
                16732
            ]
        }, 
        "2014-06-10": {
            "comments": [
                1480
            ], 
            "trades": [
                19196, 
                19191
            ]
        }, 
        "2014-06-12": {
            "comments": [
                1694
            ], 
            "trades": [
                22937, 
                22935, 
                22776
            ]
        }, 
        "2014-06-13": {
            "comments": [
                1744, 
                1731, 
                1734, 
                1715, 
                1745
            ], 
            "trades": [
                22953, 
                23004, 
                23207
            ]
        }, 
        "2014-06-14": {
            "trades": [
                25975, 
                24998
            ]
        }, 
        "2014-06-17": {
            "comments": [
                1904, 
                1915
            ], 
            "trades": [
                26973, 
                27097, 
                27016, 
                27079, 
                27000, 
                26977, 
                27073, 
                26975, 
                26993, 
                27107, 
                27093, 
                27083, 
                26972, 
                27069, 
                26974, 
                27072, 
                27014, 
                27025, 
                26969, 
                26949, 
                27092
            ]
        }, 
        "2014-06-18": {
            "comments": [
                1920
            ], 
            "trades": [
                30255
            ]
        }, 
        "2014-06-19": {
            "trades": [
                31495, 
                31500, 
                31278, 
                31503, 
                31270, 
                31309, 
                31492
            ]
        }, 
        "2014-06-20": {
            "trades": [
                31895, 
                31887, 
                31643, 
                31780
            ]
        }
    }, 
    "30": {
        "2014-05-29": {
            "comments": [
                1074
            ]
        }, 
        "2014-05-30": {
            "comments": [
                1111, 
                1116
            ], 
            "trades": [
                11195
            ]
        }, 
        "2014-05-31": {
            "comments": [
                1147
            ]
        }
    }, 
    "3022": {
        "2014-06-21": {
            "trades": [
                33968
            ]
        }
    }, 
    "3025": {
        "2014-06-21": {
            "trades": [
                33965
            ]
        }
    }, 
    "3041": {
        "2014-06-21": {
            "trades": [
                34022
            ]
        }
    }, 
    "3053": {
        "2014-06-21": {
            "trades": [
                34028
            ]
        }
    }, 
    "3065": {
        "2014-06-21": {
            "trades": [
                34036
            ]
        }
    }, 
    "3111": {
        "2014-06-21": {
            "trades": [
                34096
            ]
        }
    }, 
    "35": {
        "2014-06-12": {
            "trades": [
                22813
            ]
        }
    }, 
    "350": {
        "2014-05-29": {
            "trades": [
                10767
            ]
        }
    }, 
    "3534": {
        "2014-06-21": {
            "trades": [
                35239
            ]
        }
    }, 
    "3548": {
        "2014-06-21": {
            "trades": [
                35251
            ]
        }
    }, 
    "36": {
        "2014-05-29": {
            "trades": [
                11036, 
                11050
            ]
        }, 
        "2014-05-31": {
            "trades": [
                12918, 
                12897
            ]
        }, 
        "2014-06-03": {
            "trades": [
                14422
            ]
        }, 
        "2014-06-06": {
            "comments": [
                1335
            ]
        }
    }, 
    "367": {
        "2014-05-29": {
            "trades": [
                10744, 
                10778
            ]
        }, 
        "2014-05-30": {
            "trades": [
                11082
            ]
        }, 
        "2014-06-04": {
            "trades": [
                14505
            ]
        }
    }, 
    "372": {
        "2014-05-28": {
            "comments": [
                1060
            ]
        }, 
        "2014-06-03": {
            "comments": [
                1214
            ], 
            "trades": [
                14438, 
                14440, 
                14437
            ]
        }, 
        "2014-06-05": {
            "comments": [
                1311, 
                1297
            ], 
            "trades": [
                16628, 
                16527, 
                16635, 
                16567, 
                16540, 
                16564, 
                16600
            ]
        }, 
        "2014-06-06": {
            "comments": [
                1334, 
                1327
            ], 
            "trades": [
                16712, 
                16709, 
                16710, 
                16759, 
                16722, 
                16743, 
                16723
            ]
        }, 
        "2014-06-10": {
            "comments": [
                1481
            ], 
            "trades": [
                19291, 
                19365, 
                19346
            ]
        }, 
        "2014-06-12": {
            "comments": [
                1710, 
                1693, 
                1700, 
                1699, 
                1686, 
                1656
            ], 
            "trades": [
                22726, 
                22927, 
                22887, 
                22897, 
                22673, 
                22670, 
                22888
            ]
        }, 
        "2014-06-13": {
            "comments": [
                1742, 
                1735
            ], 
            "trades": [
                22954, 
                23147, 
                23169, 
                23154, 
                22959, 
                22956, 
                23118, 
                23216, 
                23153
            ]
        }, 
        "2014-06-14": {
            "trades": [
                26250
            ]
        }, 
        "2014-06-17": {
            "comments": [
                1914
            ], 
            "trades": [
                27007, 
                27010
            ]
        }, 
        "2014-06-19": {
            "trades": [
                31545
            ]
        }
    }, 
    "3911": {
        "2014-06-21": {
            "trades": [
                35947
            ]
        }
    }, 
    "3924": {
        "2014-06-21": {
            "trades": [
                36059
            ]
        }
    }, 
    "43": {
        "2014-05-31": {
            "trades": [
                13591
            ]
        }, 
        "2014-06-06": {
            "trades": [
                16716
            ]
        }, 
        "2014-06-07": {
            "trades": [
                17075
            ]
        }, 
        "2014-06-12": {
            "trades": [
                22701, 
                22704, 
                22703
            ]
        }, 
        "2014-06-14": {
            "trades": [
                24228
            ]
        }, 
        "2014-06-19": {
            "trades": [
                31385
            ]
        }, 
        "2014-06-20": {
            "trades": [
                31629
            ]
        }
    }, 
    "45": {
        "2014-05-27": {
            "trades": [
                9842, 
                9849, 
                9855, 
                9843, 
                9854, 
                9845
            ]
        }, 
        "2014-05-28": {
            "trades": [
                10640, 
                10316, 
                10076
            ]
        }, 
        "2014-05-29": {
            "trades": [
                11012, 
                11039, 
                11016, 
                10982
            ]
        }, 
        "2014-05-30": {
            "trades": [
                11211, 
                11340, 
                11334, 
                11169, 
                11151, 
                11209
            ]
        }, 
        "2014-05-31": {
            "trades": [
                13913, 
                13936, 
                12046, 
                12947
            ]
        }, 
        "2014-06-03": {
            "comments": [
                1215, 
                1213
            ], 
            "trades": [
                14388, 
                14431, 
                14374, 
                14443, 
                14442, 
                14424, 
                14423, 
                14426
            ]
        }, 
        "2014-06-04": {
            "trades": [
                15228, 
                14994
            ]
        }, 
        "2014-06-05": {
            "comments": [
                1315
            ], 
            "trades": [
                16652, 
                16650, 
                16359, 
                16623, 
                16360, 
                16617
            ]
        }, 
        "2014-06-06": {
            "comments": [
                1326
            ], 
            "trades": [
                16698, 
                16700, 
                16686, 
                16687, 
                16733, 
                16685, 
                16734
            ]
        }, 
        "2014-06-10": {
            "trades": [
                19304, 
                19392, 
                19367, 
                19339, 
                19393, 
                19400, 
                19340, 
                19362, 
                19301, 
                19307
            ]
        }, 
        "2014-06-13": {
            "comments": [
                1718
            ], 
            "trades": [
                23039, 
                23048
            ]
        }, 
        "2014-06-14": {
            "trades": [
                24056
            ]
        }, 
        "2014-06-17": {
            "trades": [
                26989, 
                27128
            ]
        }, 
        "2014-06-18": {
            "trades": [
                29149
            ]
        }, 
        "2014-06-19": {
            "comments": [
                2026
            ], 
            "trades": [
                31307
            ]
        }, 
        "2014-06-20": {
            "comments": [
                2065, 
                2071
            ], 
            "trades": [
                31647, 
                31736, 
                31945, 
                31713, 
                31654, 
                31707, 
                31644, 
                31729
            ]
        }
    }, 
    "50": {
        "2014-05-29": {
            "trades": [
                11038
            ]
        }, 
        "2014-05-30": {
            "trades": [
                11251
            ]
        }, 
        "2014-05-31": {
            "trades": [
                13441
            ]
        }
    }, 
    "59": {
        "2014-05-29": {
            "trades": [
                10929, 
                10889
            ]
        }, 
        "2014-05-30": {
            "trades": [
                11224, 
                11222, 
                11232, 
                11280, 
                11279, 
                11181, 
                11236, 
                11266
            ]
        }, 
        "2014-05-31": {
            "trades": [
                12907
            ]
        }, 
        "2014-06-03": {
            "comments": [
                1209
            ], 
            "trades": [
                14397, 
                14378, 
                14398, 
                14380, 
                14384, 
                14406, 
                14411, 
                14385, 
                14418, 
                14376, 
                14377, 
                14408, 
                14393
            ]
        }, 
        "2014-06-04": {
            "trades": [
                14907, 
                14893
            ]
        }, 
        "2014-06-05": {
            "trades": [
                16535, 
                16353, 
                16602, 
                16558
            ]
        }, 
        "2014-06-06": {
            "comments": [
                1331, 
                1337, 
                1333, 
                1330, 
                1320
            ], 
            "trades": [
                16729, 
                16750, 
                16726, 
                16691, 
                16725, 
                16727, 
                16694, 
                16689
            ]
        }, 
        "2014-06-12": {
            "trades": [
                22766, 
                22830, 
                22822, 
                22779, 
                22767
            ]
        }, 
        "2014-06-13": {
            "trades": [
                23200
            ]
        }, 
        "2014-06-17": {
            "trades": [
                27082, 
                27042, 
                26959, 
                26991
            ]
        }, 
        "2014-06-19": {
            "trades": [
                31486
            ]
        }, 
        "2014-06-20": {
            "comments": [
                2083, 
                2067
            ], 
            "trades": [
                31630, 
                31663, 
                31824, 
                31712, 
                31668
            ]
        }
    }, 
    "720": {
        "2014-05-28": {
            "trades": [
                10614
            ]
        }, 
        "2014-05-29": {
            "trades": [
                11018
            ]
        }, 
        "2014-06-17": {
            "trades": [
                27124, 
                27119
            ]
        }, 
        "2014-06-19": {
            "trades": [
                31283, 
                31293, 
                31284
            ]
        }
    }, 
    "796": {
        "2014-05-27": {
            "comments": [
                1044
            ], 
            "trades": [
                9841, 
                9850, 
                9839, 
                9840, 
                9838, 
                9844, 
                9837
            ]
        }, 
        "2014-05-28": {
            "trades": [
                10119, 
                10190
            ]
        }, 
        "2014-05-29": {
            "trades": [
                10811, 
                10813
            ]
        }, 
        "2014-05-30": {
            "trades": [
                11202, 
                11226
            ]
        }, 
        "2014-05-31": {
            "trades": [
                13348, 
                13236
            ]
        }, 
        "2014-06-04": {
            "comments": [
                1278
            ], 
            "trades": [
                15593, 
                15682, 
                15666, 
                14955
            ]
        }, 
        "2014-06-05": {
            "trades": [
                16668, 
                16489, 
                16482
            ]
        }, 
        "2014-06-07": {
            "comments": [
                1380
            ], 
            "trades": [
                17937
            ]
        }, 
        "2014-06-10": {
            "comments": [
                1478
            ], 
            "trades": [
                19177, 
                19287, 
                19268, 
                19259, 
                19236, 
                19174, 
                19260, 
                19265, 
                19241
            ]
        }, 
        "2014-06-11": {
            "comments": [
                1550, 
                1530
            ], 
            "trades": [
                21484, 
                21246
            ]
        }, 
        "2014-06-13": {
            "comments": [
                1722
            ], 
            "trades": [
                23081, 
                23233, 
                23074, 
                23091, 
                23095, 
                23093
            ]
        }, 
        "2014-06-18": {
            "trades": [
                28709, 
                28798
            ]
        }, 
        "2014-06-19": {
            "comments": [
                2048
            ]
        }
    }, 
    "821": {
        "2014-06-10": {
            "trades": [
                19232, 
                19216
            ]
        }, 
        "2014-06-12": {
            "trades": [
                22676
            ]
        }
    }, 
    "85": {
        "2014-05-28": {
            "trades": [
                10593
            ]
        }, 
        "2014-06-05": {
            "trades": [
                16672
            ]
        }, 
        "2014-06-06": {
            "trades": [
                16762, 
                16770, 
                16775, 
                16771
            ]
        }, 
        "2014-06-07": {
            "trades": [
                18762, 
                18810
            ]
        }, 
        "2014-06-10": {
            "trades": [
                19383, 
                19386
            ]
        }, 
        "2014-06-11": {
            "trades": [
                19818
            ]
        }, 
        "2014-06-12": {
            "comments": [
                1649
            ], 
            "trades": [
                22942
            ]
        }, 
        "2014-06-20": {
            "trades": [
                31598, 
                31609
            ]
        }
    }, 
    "971": {
        "2014-05-28": {
            "trades": [
                10469
            ]
        }
    }
}